highered/__init__.py
highered-0.2.0.dist-info/metadata.json
highered-0.2.0.dist-info/DESCRIPTION.rst
highered-0.2.0.dist-info/top_level.txt
highered-0.2.0.dist-info/RECORD
highered-0.2.0.dist-info/WHEEL
highered-0.2.0.dist-info/METADATA
